Workbook

Sheet Sales Model
A1: Parameter | B1: Value
A2: Selling Price per Unit | B2: 1200
A3: Variable Cost per Unit | B3: 700
A4: Fixed Cost | B4: 50000
A5: Expected Units Sold | B5: 150
A7: Calculated Result | B7: Amount
A8: Revenue | B8: =B2*B5
A9: Variable Cost | B9: =B3*B5
A10: Total Cost | B10: =B4+B9
A11: Profit | B11: =B8-B10
A12: Profit Margin | B12: =B11/B8

Sheet What-If Scenarios
A1: What-If Analysis – Sales Scenarios
A3: Scenario | B3: Units Sold | C3: Selling Price | D3: Revenue | E3: Total Cost | F3: Profit
A4: Low Demand | B4: 100 | C4: 1200 | D4: =B4*C4 | E4: =50000+(700*B4) | F4: =D4-E4
A5: Expected | B5: 150 | C5: 1200 | D5: =B5*C5 | E5: =50000+(700*B5) | F5: =D5-E5
A6: High Demand | B6: 200 | C6: 1200 | D6: =B6*C6 | E6: =50000+(700*B6) | F6: =D6-E6
A7: Price Increase | B7: 150 | C7: 1400 | D7: =B7*C7 | E7: =50000+(700*B7) | F7: =D7-E7

Sheet Goal Seek
A1: Goal Seek Practical
A2: Goal | B2: Find the units needed to earn ₹100,000 profit.
A3: Current Profit Formula | B3: =(Selling Price × Units) − (Fixed Cost + Variable Cost × Units)
A4: Selling Price | B4: ₹1,200
A5: Variable Cost | B5: ₹700
A6: Fixed Cost | B6: ₹50,000
A7: Target Profit | B7: ₹1,00,000
A9: Excel Steps
A10: 1 | B10: Set up the sales model with a Profit formula.
A11: 2 | B11: Go to Data → What-If Analysis → Goal Seek.
A12: 3 | B12: Set cell: Profit cell.
A13: 4 | B13: To value: 100000.
A14: 5 | B14: By changing cell: Units Sold cell.
A15: 6 | B15: Click OK and review the required units.

Sheet Scenario Chart
A1: Profit Comparison by Scenario
A3: Scenario | B3: Profit
A4: ='What-If Scenarios'!A4 | B4: ='What-If Scenarios'!F4
A5: ='What-If Scenarios'!A5 | B5: ='What-If Scenarios'!F5
A6: ='What-If Scenarios'!A6 | B6: ='What-If Scenarios'!F6
A7: ='What-If Scenarios'!A7 | B7: ='What-If Scenarios'!F7

Sheet Notes
A1: Day 16 – What-If Analysis & Goal Seek
A3: What I Practiced
A4: • Built a simple sales and profit model.
A5: • Compared Low Demand, Expected, High Demand and Price Increase scenarios.
A6: • Used formulas to calculate Revenue, Total Cost and Profit.
A7: • Learned how Goal Seek can find the input required to reach a target profit.
